graphene_federation/__init__.py
graphene_federation/entity.py
graphene_federation/extend.py
graphene_federation/main.py
graphene_federation/provides.py
graphene_federation/service.py
graphene_federation/types.py
cxa_graphene_federation-1.0.0b1.dist-info/LICENSE.txt
cxa_graphene_federation-1.0.0b1.dist-info/METADATA
cxa_graphene_federation-1.0.0b1.dist-info/WHEEL
cxa_graphene_federation-1.0.0b1.dist-info/top_level.txt
cxa_graphene_federation-1.0.0b1.dist-info/RECORD
