Metadata-Version: 2.1
Name: cxa-graphene-federation
Version: 1.0.0b1
Summary: Federation implementation for graphene
Home-page: https://github.com/preply/graphene-federation
Author: Igor Kasianov
Author-email: super.hang.glider@gmail.com
License: MIT
Download-URL: https://github.com/preply/graphene-federation/archive/1.0.0b1.tar.gz
Keywords: graphene,gql,federation
Platform: UNKNOWN
Classifier: Development Status :: 5 - Production/Stable
Classifier: Intended Audience :: Developers
Classifier: Topic :: Software Development :: Libraries
Classifier: Programming Language :: Python :: 3.6
Requires-Dist: graphene (<4,>=3.0.0b5)
